CHANGES.rst
LICENSE.rst
MANIFEST.in
README.rst
setup.cfg
setup.py
examples/requests.py
scriptstrap/__init__.py
scriptstrap/scriptstrap.py
scriptstrap.egg-info/PKG-INFO
scriptstrap.egg-info/SOURCES.txt
scriptstrap.egg-info/dependency_links.txt
scriptstrap.egg-info/not-zip-safe
scriptstrap.egg-info/top_level.txt