Metadata-Version: 1.1
Name: scriptstrap
Version: 0.0.1
Summary: Simple bootstrapping of python scripts
Home-page: https://github.com/postlund/scriptstrap
Author: Pierre Ståhl
Author-email: pierre.staahl@gmail.com
License: MIT
Platform: any
Classifier: Development Status :: 3 - Alpha
Classifier: Intended Audience :: Developers
Classifier: License :: OSI Approved :: MIT License
Classifier: Operating System :: OS Independent
Classifier: Programming Language :: Python :: 2.7
Classifier: Programming Language :: Python :: 3.4
Classifier: Programming Language :: Python :: 3.5
Classifier: Programming Language :: Python :: 3.6
Classifier: Topic :: Software Development :: Libraries
Classifier: Topic :: Utilities
